{
  "version": "3.0.0",
  "gates": [
    {
      "id": "G1",
      "name": "Outcome Traceability Gate",
      "description": "Minimum outcome measurement capability required for higher maturity",
      "label": "Outcome traceability ≥ 4",
      "parameters": ["cust.outcome_trace"],
      "logic": "AND",
      "threshold": 4.0,
      "operator": ">=",
      "blockingLevel": "band3",
      "rationale": "Cannot achieve higher maturity without measurable outcome tracking"
    },
    {
      "id": "G2", 
      "name": "Delivery Flow Gate",
      "description": "Core delivery capabilities must be established",
      "label": "Lead time ≥ 4 AND Release safety ≥ 4",
      "parameters": ["deliv.lead_time", "deliv.release_safety"],
      "logic": "AND", 
      "threshold": 4.0,
      "operator": ">=",
      "blockingLevel": "band4",
      "rationale": "Delivery fundamentals are prerequisite for organizational maturity"
    },
    {
      "id": "G3",
      "name": "Reliability Gate", 
      "description": "System reliability must be measurable and managed",
      "label": "SLOs & MTTR ≥ 4",
      "parameters": ["reliab.slos_product", "reliab.mttr_budget"],
      "logic": "AND",
      "threshold": 4.0, 
      "operator": ">=",
      "blockingLevel": "band4",
      "rationale": "Reliability measurement is essential for scalable operations"
    },
    {
      "id": "G4",
      "name": "Customer Alignment Gate",
      "description": "Customer understanding and measurement literacy required", 
      "label": "Customer proximity & KPI literacy ≥ 4",
      "parameters": ["cust.proximity", "cust.kpi_literacy"],
      "logic": "AND",
      "threshold": 4.0,
      "operator": ">=",
      "blockingLevel": "band4",
      "rationale": "Customer alignment prevents feature factories and waste"
    },
    {
      "id": "G5",
      "name": "Strategic Alignment Gate",
      "description": "Strategy must be connected to execution via OKRs",
      "label": "Strategy→OKR ≥ 3.5", 
      "parameters": ["strat.okr_link"],
      "logic": "AND",
      "threshold": 3.5,
      "operator": ">=",
      "blockingLevel": "band3",
      "rationale": "Strategic alignment prevents unfocused execution"
    },
    {
      "id": "G6",
      "name": "Financial Transparency Gate",
      "description": "Cost management and budget transparency required",
      "label": "Cost-to-serve & Squad budget ≥ 3.5",
      "parameters": ["econ.cost_to_serve", "econ.squad_budget"],
      "logic": "AND",
      "threshold": 3.5,
      "operator": ">=", 
      "blockingLevel": "band4",
      "rationale": "Financial transparency enables outcome-driven decisions"
    }
  ],
  "caps": [
    {
      "id": "C1",
      "name": "Delivery Flow Cap",
      "description": "Cap overall maturity if core delivery practices are weak",
      "label": "Cap 2.4 if Lead time < 3 or Release < 3", 
      "parameters": ["deliv.lead_time", "deliv.release_safety"],
      "logic": "OR",
      "capValue": 2.4,
      "conditions": [
        {
          "parameter": "deliv.lead_time",
          "operator": "<",
          "value": 3.0
        },
        {
          "parameter": "deliv.release_safety",
          "operator": "<", 
          "value": 3.0
        }
      ],
      "rationale": "Poor delivery flow fundamentally limits organizational capability"
    },
    {
      "id": "C2",
      "name": "Customer Proximity Cap",
      "description": "Cap maturity if customer understanding is minimal",
      "label": "Cap 2.9 if Customer proximity ≤ 2",
      "parameters": ["cust.proximity"],
      "logic": "LE",
      "capValue": 2.9,
      "conditions": [
        {
          "parameter": "cust.proximity", 
          "operator": "<=",
          "value": 2.0
        }
      ],
      "rationale": "Without customer proximity, teams build features rather than outcomes"
    },
    {
      "id": "C3",
      "name": "Outcome Traceability Cap",
      "description": "Cap maturity if outcome measurement is absent",
      "label": "Cap 3.0 if Outcome traceability ≤ 2",
      "parameters": ["cust.outcome_trace"],
      "logic": "LE", 
      "capValue": 3.0,
      "conditions": [
        {
          "parameter": "cust.outcome_trace",
          "operator": "<=", 
          "value": 2.0
        }
      ],
      "rationale": "Cannot demonstrate higher maturity without measuring business outcomes"
    }
  ],
  "validationRules": [
    {
      "id": "tier1_minimum",
      "name": "Tier 1 Foundation Requirements",
      "description": "Core practices must be established before advancing",
      "parameters": ["deliv.lead_time", "eng.test_strategy", "cust.proximity"],
      "minimumCompliance": 0.6,
      "blockingLevel": "tier2",
      "message": "Complete foundational practices before advancing to tier 2"
    },
    {
      "id": "tier2_minimum", 
      "name": "Tier 2 Capability Requirements",
      "description": "Established capabilities required for advanced practices",
      "parameters": ["reliab.slos_product", "arch.modularity", "prod.discovery"],
      "minimumCompliance": 0.7,
      "blockingLevel": "tier3",
      "message": "Establish core capabilities before advancing to tier 3"
    }
  ]
}